odoo/addons/ssi_hr_holiday/README.rst
odoo/addons/ssi_hr_holiday/__init__.py
odoo/addons/ssi_hr_holiday/__manifest__.py
odoo/addons/ssi_hr_holiday/data/approval_template_data.xml
odoo/addons/ssi_hr_holiday/data/base_automation_data.xml
odoo/addons/ssi_hr_holiday/data/ir_actions_server_data.xml
odoo/addons/ssi_hr_holiday/data/ir_cron.xml
odoo/addons/ssi_hr_holiday/data/ir_sequence_data.xml
odoo/addons/ssi_hr_holiday/data/policy_template_data.xml
odoo/addons/ssi_hr_holiday/data/sequence_template_data.xml
odoo/addons/ssi_hr_holiday/demo/hr_leave_type_data_demo.xml
odoo/addons/ssi_hr_holiday/models/__init__.py
odoo/addons/ssi_hr_holiday/models/hr_leave.py
odoo/addons/ssi_hr_holiday/models/hr_leave_allocation.py
odoo/addons/ssi_hr_holiday/models/hr_leave_type.py
odoo/addons/ssi_hr_holiday/models/hr_timesheet.py
odoo/addons/ssi_hr_holiday/models/hr_timesheet_attendance_schedule.py
odoo/addons/ssi_hr_holiday/security/ir.model.access.csv
odoo/addons/ssi_hr_holiday/security/ir_module_category_data.xml
odoo/addons/ssi_hr_holiday/security/ir_rule_data.xml
odoo/addons/ssi_hr_holiday/security/res_group_data.xml
odoo/addons/ssi_hr_holiday/static/description/icon.png
odoo/addons/ssi_hr_holiday/views/hr_leave_allocation_views.xml
odoo/addons/ssi_hr_holiday/views/hr_leave_type_views.xml
odoo/addons/ssi_hr_holiday/views/hr_leave_views.xml
odoo/addons/ssi_hr_holiday/views/hr_timesheet_views.xml
odoo14_addon_ssi_hr_holiday-14.0.1.5.0.dist-info/METADATA
odoo14_addon_ssi_hr_holiday-14.0.1.5.0.dist-info/WHEEL
odoo14_addon_ssi_hr_holiday-14.0.1.5.0.dist-info/top_level.txt
odoo14_addon_ssi_hr_holiday-14.0.1.5.0.dist-info/RECORD
